pyttman_mongoengine_plugin/__init__.py
pyttman_plugin_mongoengine-1.0.7.dist-info/METADATA
pyttman_plugin_mongoengine-1.0.7.dist-info/WHEEL
pyttman_plugin_mongoengine-1.0.7.dist-info/top_level.txt
pyttman_plugin_mongoengine-1.0.7.dist-info/RECORD
