Metadata-Version: 2.4
Name: pyttman_plugin_mongoengine
Version: 1.0.7
Summary: Mongoengine (MongoDB) plugin for Pyttman apps, allowing seamless integration with MongoEngine and Pyttman.
Home-page: https://github.com/Hashmap-Software-Agency/Pyttman-Plugins
Author: Simon Olofsson, Pyttman framework founder and maintainer.
Author-email: simon@hashmap.se
License: MIT
Classifier: License :: OSI Approved :: MIT License
Classifier: Programming Language :: Python :: 3 :: Only
Classifier: Programming Language :: Python :: 3.10
Classifier: Operating System :: OS Independent
Requires-Python: >=3.11
Requires-Dist: mongoengine
Requires-Dist: pyttman_plugin_base
Dynamic: author
Dynamic: author-email
Dynamic: classifier
Dynamic: description-content-type
Dynamic: home-page
Dynamic: license
Dynamic: requires-dist
Dynamic: requires-python
Dynamic: summary
